amclient/__init__.py
amclient/amclient.py
amclient/amclientargs.py
amclient/defaults.py
amclient/errors.py
amclient/loggingconfig.py
amclient/utils.py
amclient/version.py
amclient-1.6.0.dist-info/licenses/LICENSE
amclient-1.6.0.dist-info/METADATA
amclient-1.6.0.dist-info/WHEEL
amclient-1.6.0.dist-info/entry_points.txt
amclient-1.6.0.dist-info/top_level.txt
amclient-1.6.0.dist-info/RECORD
